PacketStats/__init__.py
PacketStats/convertion.py
PacketStats/statistics.py
PacketStats-1.4.dist-info/LICENSE
PacketStats-1.4.dist-info/METADATA
PacketStats-1.4.dist-info/WHEEL
PacketStats-1.4.dist-info/top_level.txt
PacketStats-1.4.dist-info/RECORD
