Metadata-Version: 2.1
Name: PacketStats
Version: 1.4
Summary: Package to work with pcap files and converting them to txt,csv and then creating stats
Home-page: http://github.com/mattkozlowski/packet-stats
Author: Matt Kozlowski
Author-email: mateusz.a.kozlowski@gmail.com
License: MIT
Platform: UNKNOWN
